postbound/__init__.py
postbound/__init__.pyi
postbound/_base.py
postbound/_core.py
postbound/_hints.py
postbound/_pipelines.py
postbound/_qep.py
postbound/_stages.py
postbound/bench.py
postbound/duckdb.py
postbound/mysql.py
postbound/parser.py
postbound/postgres.py
postbound/relalg.py
postbound/transform.py
postbound/validation.py
postbound/workloads.py
postbound/db/__init__.py
postbound/db/_db.py
postbound/experiments/__init__.py
postbound/experiments/__init__.pyi
postbound/experiments/ceb.py
postbound/experiments/querygen.py
postbound/opt/__init__.py
postbound/opt/__init__.pyi
postbound/opt/_analysis.py
postbound/opt/_cardinalities.py
postbound/opt/_helpers.py
postbound/opt/_joingraph.py
postbound/opt/dynprog.py
postbound/opt/enumeration.py
postbound/opt/native.py
postbound/opt/noopt.py
postbound/opt/presets.py
postbound/opt/randomized.py
postbound/opt/tonic.py
postbound/opt/ues.py
postbound/qal/__init__.py
postbound/qal/_formatter.py
postbound/qal/_qal.py
postbound/util/__init__.py
postbound/util/__init__.pyi
postbound/util/_errors.py
postbound/util/collections.py
postbound/util/df.py
postbound/util/dicts.py
postbound/util/jsonize.py
postbound/util/logging.py
postbound/util/misc.py
postbound/util/num.py
postbound/util/nx.py
postbound/util/proc.py
postbound/util/stats.py
postbound/util/system.py
postbound/util/typing.py
postbound/vis/__init__.py
postbound/vis/__init__.pyi
postbound/vis/fdl.py
postbound/vis/graphs.py
postbound/vis/optimizer.py
postbound/vis/plots.py
postbound/vis/tonic.py
postbound/vis/trees.py
postbound-0.20.1.dist-info/licenses/LICENSE.txt
postbound-0.20.1.dist-info/METADATA
postbound-0.20.1.dist-info/WHEEL
postbound-0.20.1.dist-info/top_level.txt
postbound-0.20.1.dist-info/RECORD
