Metadata-Version: 2.4
Name: PostBOUND
Version: 0.20.1
Summary: PostBOUND is a research framework to prototype and benchmark database query optimizers
Author-email: Rico Bergmann <rico.bergmann1@tu-dresden.de>
License-Expression: Apache-2.0
Project-URL: Homepage, https://github.com/rbergm/PostBOUND
Classifier: Programming Language :: Python :: 3
Classifier: Intended Audience :: Science/Research
Classifier: Topic :: Database :: Database Engines/Servers
Classifier: Topic :: Scientific/Engineering
Classifier: Operating System :: OS Independent
Requires-Python: >=3.12
License-File: LICENSE.txt
Requires-Dist: lazy-loader~=0.4
Requires-Dist: levenshtein~=0.27
Requires-Dist: natsort~=8.4
Requires-Dist: networkx~=3.5
Requires-Dist: numpy~=2.3
Requires-Dist: pandas~=2.3
Requires-Dist: pglast~=7.10
Requires-Dist: psycopg[binary]~=3.2
Requires-Dist: tqdm~=4.67
Provides-Extra: vis
Requires-Dist: matplotlib~=3.10; extra == "vis"
Requires-Dist: seaborn~=0.13; extra == "vis"
Requires-Dist: graphviz~=0.21; extra == "vis"
Provides-Extra: duckdb
Requires-Dist: quacklab~=1.4; extra == "duckdb"
Provides-Extra: mysql
Requires-Dist: mysql-connector-python~=9.5; extra == "mysql"
Dynamic: license-file
